LICENSE
README
downpour-debug.sh
ez_setup.py
setup.py
Downpour.egg-info/PKG-INFO
Downpour.egg-info/SOURCES.txt
Downpour.egg-info/dependency_links.txt
Downpour.egg-info/not-zip-safe
Downpour.egg-info/requires.txt
Downpour.egg-info/top_level.txt
bin/downpour-remote
bin/downpour-torrent-handler
bin/downpourd
cfg/debug.cfg
cfg/downpour.cfg
downpour/__init__.py
downpour/core/__init__.py
downpour/core/application.py
downpour/core/daemon.py
downpour/core/db.py
downpour/core/manager.py
downpour/core/models.py
downpour/core/organizer.py
downpour/core/plugins.py
downpour/core/sqlitefk.py
downpour/download/__init__.py
downpour/download/http.py
downpour/download/torrent.py
downpour/feed/__init__.py
downpour/feed/checker.py
downpour/remote/__init__.py
downpour/remote/commands.py
downpour/remote/protocol.py
downpour/remote/server.py
downpour/remote/types.py
downpour/web/__init__.py
downpour/web/account.py
downpour/web/auth.py
downpour/web/browse.py
downpour/web/common.py
downpour/web/downloads.py
downpour/web/feeds.py
downpour/web/libraries.py
downpour/web/search.py
downpour/web/settings.py
downpour/web/site.py
downpour/web/status.py
downpour/web/users.py
downpour/web/work.py
downpour/web/templates/base.html
downpour/web/templates/account/edit.html
downpour/web/templates/account/index.html
downpour/web/templates/account/login.html
downpour/web/templates/account/saved.html
downpour/web/templates/browse/confirmdelete.html
downpour/web/templates/browse/directory.html
downpour/web/templates/downloads/detail.html
downpour/web/templates/downloads/detail_application_x-bittorrent.html
downpour/web/templates/downloads/history.html
downpour/web/templates/downloads/index.html
downpour/web/templates/downloads/status-js.html
downpour/web/templates/errors/error.html
downpour/web/templates/feeds/form.html
downpour/web/templates/feeds/index.html
downpour/web/templates/libraries/index.html
downpour/web/templates/media/css/style.css
downpour/web/templates/media/images/add.gif
downpour/web/templates/media/images/confirm-small.png
downpour/web/templates/media/images/confirm.png
downpour/web/templates/media/images/delete.gif
downpour/web/templates/media/images/delete.png
