Metadata-Version: 1.0
Name: Downpour
Version: 0.2
Summary: Downpour is a web-based BitTorrent client
Home-page: http://home.jongsma.org/software/downpour/
Author: Jeremy Jongsma
Author-email: jeremy@jongsma.org
License: GPLv2
Platform: UNKNOWN
